minefob.py
minefob-2.0.0.dist-info/LICENSE
minefob-2.0.0.dist-info/METADATA
minefob-2.0.0.dist-info/WHEEL
minefob-2.0.0.dist-info/top_level.txt
minefob-2.0.0.dist-info/RECORD
