Metadata-Version: 2.1
Name: minefob
Version: 2.0.0
Summary: (Deprecated) Module to control Minehut servers via Python
Author-email: Caleb North <contact@fivesixfive.dev>
License: MIT License
Classifier: Programming Language :: Python :: 3
Classifier: License :: OSI Approved :: MIT License
Classifier: Operating System :: OS Independent
Requires-Python: >=3.6
License-File: LICENSE
